assassin_api/__init__.py
assassin_api/api.py
assassin_api/decorators.py
assassin_api/exceptions.py
assassin_api/mapping_models.py
assassin_api/queries.py
assassin_api/session.py
assassin_api/validators.py
assassin_api_python-0.0.4.dist-info/LICENSE
assassin_api_python-0.0.4.dist-info/METADATA
assassin_api_python-0.0.4.dist-info/WHEEL
assassin_api_python-0.0.4.dist-info/top_level.txt
assassin_api_python-0.0.4.dist-info/RECORD
