Metadata-Version: 2.1
Name: assassin-api-python
Version: 0.0.4
Summary: Assassin Asset Lib Python API
Author: Assassin Asset Lib
Author-email: is@silasveta.com.com
License: UNKNOWN
Platform: UNKNOWN
Classifier: Programming Language :: Python :: 3
Classifier: License :: OSI Approved :: MIT License
Classifier: Operating System :: OS Independent
Requires-Python: >=3.6
License-File: LICENSE
Requires-Dist: requests
